spatiafi/__init__.py
spatiafi/__main__.py
spatiafi/_version.py
spatiafi/async_queue.py
spatiafi/auth.py
spatiafi/session.py
spatiafi/gdal_auth/__init__.py
spatiafi/gdal_auth/__main__.py
spatiafi/gdal_auth/cli.py
spatiafi/gdal_auth/gdal_auth.py
spatiafi-1.8.0.dist-info/LICENSE
spatiafi-1.8.0.dist-info/METADATA
spatiafi-1.8.0.dist-info/WHEEL
spatiafi-1.8.0.dist-info/entry_points.txt
spatiafi-1.8.0.dist-info/top_level.txt
spatiafi-1.8.0.dist-info/RECORD
