Metadata-Version: 2.1
Name: spatiafi
Version: 1.8.0
Summary: Python library for interacting with the SpatiaFi API
Home-page: https://github.com/climateengine/py-spatiafi
Author: Climate Engine Team
Author-email: admin@climateengine.com
Requires-Python: >=3.8
License-File: LICENSE
Requires-Dist: authlib
Requires-Dist: click
Requires-Dist: google-api-core
Requires-Dist: google-auth
Requires-Dist: google-auth-oauthlib
Requires-Dist: httpx
Requires-Dist: pandas
Requires-Dist: platformdirs >=3.2.0
Requires-Dist: requests
Provides-Extra: dev
Requires-Dist: autoflake ; extra == 'dev'
Requires-Dist: black ; extra == 'dev'
Requires-Dist: build ; extra == 'dev'
Requires-Dist: flake8 ; extra == 'dev'
Requires-Dist: flake8-pyproject ; extra == 'dev'
Requires-Dist: isort ; extra == 'dev'
Requires-Dist: keyring ; extra == 'dev'
Requires-Dist: keyrings.google-artifactregistry-auth ; extra == 'dev'
Requires-Dist: mypy ; extra == 'dev'
Requires-Dist: pandas ; extra == 'dev'
Requires-Dist: pip-tools ; extra == 'dev'
Requires-Dist: pre-commit ; extra == 'dev'
Requires-Dist: pytest ; extra == 'dev'
Requires-Dist: setuptools-scm[toml] >=7.1.0 ; extra == 'dev'
Requires-Dist: tox ; extra == 'dev'
Requires-Dist: twine ; extra == 'dev'
Requires-Dist: wheel ; extra == 'dev'
